pygame_brickbreaker/__init__.py
pygame_brickbreaker/bounce.wav
pygame_brickbreaker/game.py
pygame_brickbreaker/lost.ogg
pygame_brickbreaker/won.wav
pygame_brickbreaker-1.0.2.dist-info/licenses/LICENSE
pygame_brickbreaker-1.0.2.dist-info/METADATA
pygame_brickbreaker-1.0.2.dist-info/WHEEL
pygame_brickbreaker-1.0.2.dist-info/entry_points.txt
pygame_brickbreaker-1.0.2.dist-info/top_level.txt
pygame_brickbreaker-1.0.2.dist-info/RECORD
