Metadata-Version: 2.4
Name: pygame-brickbreaker
Version: 1.0.2
Summary: 🎮 A classic brick breaker game built with Python and Pygame.
Author-email: Priyanshu Raj <prmahatha@gmail.com>
Requires-Python: >=3.7
License-File: LICENSE
Requires-Dist: pygame
Dynamic: license-file
